MANIFEST.in
README.rst
pyproject.toml
requirements.txt
setup.cfg
setup.py
t_ocr/__init__.py
t_ocr/_config.py
t_ocr/exceptions.py
t_ocr/free_ocr.py
t_ocr/logger.py
t_ocr/ocr.py
t_ocr/okta.py
t_ocr/pages.py
t_ocr/textract.py
t_ocr.egg-info/PKG-INFO
t_ocr.egg-info/SOURCES.txt
t_ocr.egg-info/dependency_links.txt
t_ocr.egg-info/not-zip-safe
t_ocr.egg-info/requires.txt
t_ocr.egg-info/top_level.txt
t_ocr/ocr_tools/__init__.py
t_ocr/ocr_tools/address.py
t_ocr/ocr_tools/fields_search.py
t_ocr/ocr_tools/models.py
t_ocr/ocr_tools/ocr_tools.py
t_ocr/ocr_tools/validators.py
t_ocr/ocr_tools/patterns/__init__.py
t_ocr/ocr_tools/patterns/patterns.py
tests/test_t_ocr.py