Metadata-Version: 2.4
Name: t_ocr
Version: 1.5.5
Summary: Thoughtful OCR Package
Home-page: https://www.thoughtful.ai/
Author: Thoughtful
Author-email: support@thoughtfulautomation.com
Keywords: thoughtful-ocr,t-ocr,t_ocr
Classifier: Intended Audience :: Developers
Classifier: Natural Language :: English
Classifier: Programming Language :: Python :: 3
Classifier: Programming Language :: Python :: 3.8
Classifier: Programming Language :: Python :: 3.9
Classifier: Programming Language :: Python :: 3.10
Classifier: Programming Language :: Python :: 3.11
Requires-Python: >=3.8
Requires-Dist: requests==2.32.3
Requires-Dist: boto3==1.38.27
Requires-Dist: datefinder==0.7.3
Requires-Dist: email-validator==2.2.0
Requires-Dist: pypdf==6.1.3
Requires-Dist: usaddress==0.5.14
Requires-Dist: pyotp==2.9.0
Dynamic: author
Dynamic: author-email
Dynamic: classifier
Dynamic: description
Dynamic: home-page
Dynamic: keywords
Dynamic: requires-dist
Dynamic: requires-python
Dynamic: summary
